odcantoolkit/filemanager.py
odcantoolkit/cli.py
odcantoolkit/prompt.py
odcantoolkit/__init__.py
odcantoolkit/parser/abstract.py
odcantoolkit/parser/csv.py
odcantoolkit/parser/__init__.py
odcantoolkit/parser/factory.py
odcantoolkit/CKAN/CKAN_API.py
odcantoolkit/CKAN/__init__.py
odcantoolkit/output/generation.py
odcantoolkit/output/__init__.py
odcantoolkit/database/mongodb.py
odcantoolkit/database/__init__.py
odcantoolkit/encoding/guessing.py
odcantoolkit/encoding/__init__.py
odcantoolkit-0.1.3.dist-info/METADATA
odcantoolkit-0.1.3.dist-info/entry_points.txt
odcantoolkit-0.1.3.dist-info/WHEEL
odcantoolkit-0.1.3.dist-info/RECORD
odcantoolkit-0.1.3.dist-info/metadata.json
odcantoolkit-0.1.3.dist-info/top_level.txt
odcantoolkit-0.1.3.dist-info/DESCRIPTION.rst
