Metadata-Version: 2.0
Name: odcantoolkit
Version: 0.1.3
Summary: Python tool to fetch data from Canada's open data portal
Home-page: https://github.com/gchamp20/odcantoolkit
Author: Guillaume Champagne
Author-email: guillaume.champagne@polymtl.ca
License: MIT
Keywords: canada open data json mongodb
Platform: UNKNOWN
Classifier: Development Status :: 3 - Alpha
Classifier: Intended Audience :: Developers
Classifier: Topic :: Utilities
Classifier: License :: OSI Approved :: MIT License
Classifier: Programming Language :: Python :: 3
Requires-Dist: pymongo
